7-segment-decoder/decoder7seg.vhd
library IEEE;
use IEEE.std_logic_1164.all;

entity decoder7seg is 
    port(
        binary_in : in std_logic_vector(3 downto 0);
        seg_disp_out : out std_logic_vector(6 downto 0)
    );
end decoder7seg;

architecture decoder7seg_arc of decoder7seg is
    begin
        with binary_in select
            seg_disp_out <= "0111111" when "0000", -- 0
                            "0000110" when "0001", -- 1
                            "1011011" when "0010", -- 2
                            "1001111" when "0011", -- 3
                            "0100110" when "0100", -- 4
                            "1101101" when "0101", -- 5
                            "1111101" when "0110", -- 6
                            "0000111" when "0111", -- 7
                            "1111111" when "1000", -- 8
                            "1101111" when "1001", -- 9
                            "1110111" when "1010", -- A
                            "1111100" when "1011", -- B
                            "1011000" when "1100", -- C
                            "1011110" when "1101", -- D
                            "1111001" when "1110", -- E
                            "1110001" when "1111", -- F
                            "-------" when others;
    end decoder7seg_arc;

7-segment-decoder/decoder7seg_tb.vhd
library IEEE;
use IEEE.std_logic_1164.all;
use IEEE.numeric_std.all;

entity decoder7seg_tb is 
end decoder7seg_tb;

architecture decoder7seg_tb_arc of decoder7seg_tb is
    signal tb_binary_in : std_logic_vector(3 downto 0) := "0000";
    signal tb_seg_disp_out : std_logic_vector(6 downto 0);

begin 

    UUT: entity work.decoder7seg(decoder7seg_arc)
        port map(
            binary_in => tb_binary_in,
            seg_disp_out => tb_seg_disp_out
        );

    stim_proc: process
    begin
        -- Zahl 0
        tb_binary_in <= "0000";
        wait for 10 ns;
        
        -- Zahl 1
        tb_binary_in <= "0001";
        wait for 10 ns;
        
        -- Zahl 2
        tb_binary_in <= "0010";
        wait for 10 ns;
        
        -- Zahl 3
        tb_binary_in <= "0011";
        wait for 10 ns;
        
        -- Zahl 4
        tb_binary_in <= "0100";
        wait for 10 ns;
        
        -- Zahl 5
        tb_binary_in <= "0101";
        wait for 10 ns;
        
        -- Zahl 6
        tb_binary_in <= "0110";
        wait for 10 ns;
        
        -- Zahl 7
        tb_binary_in <= "0111";
        wait for 10 ns;
        
        -- Zahl 8
        tb_binary_in <= "1000";
        wait for 10 ns;
        
        -- Zahl 9
        tb_binary_in <= "1001";
        wait for 10 ns;
        
        -- Zahl 10 (A)
        tb_binary_in <= "1010";
        wait for 10 ns;
        
        -- Zahl 11 (B)
        tb_binary_in <= "1011";
        wait for 10 ns;
        
        -- Zahl 12 (C)
        tb_binary_in <= "1100";
        wait for 10 ns;
        
        -- Zahl 13 (D)
        tb_binary_in <= "1101";
        wait for 10 ns;
        
        -- Zahl 14 (E)
        tb_binary_in <= "1110";
        wait for 10 ns;
        
        -- Zahl 15 (F)
        tb_binary_in <= "1111";
        wait for 10 ns;
        wait;
    end process;
end decoder7seg_tb_arc;

7-segment-decoder/wave.vcd
$date
  Mon Jul 13 16:49:49 2026
$end
$version
  GHDL v0
$end
$timescale
  1 fs
$end
$scope module standard $end
$upscope $end
$scope module std_logic_1164 $end
$upscope $end
$scope module numeric_std $end
$upscope $end
$scope module decoder7seg_tb $end
$var reg 4 ! tb_binary_in[3:0] $end
$var reg 7 " tb_seg_disp_out[6:0] $end
$scope module uut $end
$var reg 4 # binary_in[3:0] $end
$var reg 7 $ seg_disp_out[6:0] $end
$upscope $end
$upscope $end
$enddefinitions $end
#0
b0000 !
b0111111 "
b0000 #
b0111111 $
#10000000
b0001 !
b0000110 "
b0001 #
b0000110 $
#20000000
b0010 !
b1011011 "
b0010 #
b1011011 $
#30000000
b0011 !
b1001111 "
b0011 #
b1001111 $
#40000000
b0100 !
b0100110 "
b0100 #
b0100110 $
#50000000
b0101 !
b1101101 "
b0101 #
b1101101 $
#60000000
b0110 !
b1111101 "
b0110 #
b1111101 $
#70000000
b0111 !
b0000111 "
b0111 #
b0000111 $
#80000000
b1000 !
b1111111 "
b1000 #
b1111111 $
#90000000
b1001 !
b1101111 "
b1001 #
b1101111 $
#100000000
b1010 !
b1110111 "
b1010 #
b1110111 $
#110000000
b1011 !
b1111100 "
b1011 #
b1111100 $
#120000000
b1100 !
b1011000 "
b1100 #
b1011000 $
#130000000
b1101 !
b1011110 "
b1101 #
b1011110 $
#140000000
b1110 !
b1111001 "
b1110 #
b1111001 $
#150000000
b1111 !
b1110001 "
b1111 #
b1110001 $
